pytest_pexpect/__init__.py
pytest_pexpect/pexpect_plugin.py
pytest_pexpect-0.3.0.dist-info/licenses/LICENSE
pytest_pexpect-0.3.0.dist-info/METADATA
pytest_pexpect-0.3.0.dist-info/WHEEL
pytest_pexpect-0.3.0.dist-info/entry_points.txt
pytest_pexpect-0.3.0.dist-info/top_level.txt
pytest_pexpect-0.3.0.dist-info/RECORD
