Metadata-Version: 2.4
Name: pytest-pexpect
Version: 0.3.0
Summary: Pytest pexpect plugin.
Author-email: Michal Novak <it.novakmi@gmail.com>
Maintainer-email: Michal Novak <it.novakmi@gmail.com>
License: MIT License
Project-URL: Repository, https://github.com/novakmi/pytest-pexpect
Classifier: Framework :: Pytest
Classifier: Development Status :: 4 - Beta
Classifier: Intended Audience :: Developers
Classifier: Topic :: Software Development :: Testing
Classifier: Operating System :: OS Independent
Classifier: Programming Language :: Python
Classifier: Programming Language :: Python :: 3.8
Classifier: Programming Language :: Python :: 3.9
Classifier: Programming Language :: Python :: 3.10
Classifier: Programming Language :: Python :: 3.11
Classifier: Programming Language :: Python :: 3.12
Classifier: Programming Language :: Python :: 3 :: Only
Classifier: Programming Language :: Python :: Implementation :: CPython
Classifier: Programming Language :: Python :: Implementation :: PyPy
Classifier: License :: OSI Approved :: MIT License
Requires-Python: >=3.8
License-File: LICENSE
Requires-Dist: pytest>=6.2.0
Requires-Dist: pexpect>=4.8.0
Dynamic: license-file
